LICENSE.txt
README.md
__init__.py
rocket.py
setup.py
rocket_sanaa.egg-info/PKG-INFO
rocket_sanaa.egg-info/SOURCES.txt
rocket_sanaa.egg-info/dependency_links.txt
rocket_sanaa.egg-info/top_level.txt