Metadata-Version: 2.1
Name: rocket-sanaa
Version: 1.0.0
Summary: An awesome package that creates rockets and shuttles
Home-page: http://pypi.python.org/pypi/rocket/
Author: sanaa bensaid
Author-email: <s.bensaid@esi-sba.dz
License: LICENSE.txt
License-File: LICENSE.txt
